schema_agent/__init__.py
schema_agent/consts.py
schema_agent/errors.py
schema_agent/llm.py
schema_agent/parse.py
schema_agent/str.py
schema_agent/types.py
schema_agent/utils.py
schema_agent-0.1.4.dist-info/METADATA
schema_agent-0.1.4.dist-info/WHEEL
schema_agent-0.1.4.dist-info/licenses/LICENSE
schema_agent-0.1.4.dist-info/RECORD
