Metadata-Version: 2.4
Name: schema_agent
Version: 0.1.4
Summary: Practical, robust structured generation with retries using Pydantic schemas
Project-URL: Homepage, https://github.com/pymc-labs/schema-agent
Project-URL: Repository, https://github.com/pymc-labs/schema-agent
Project-URL: Issues, https://github.com/pymc-labs/schema-agent/issues
Author-email: ulfaslak <ulfaslak@gmail.com>
License:                                  Apache License
License-File: LICENSE
Keywords: langchain,langgraph,llm,pydantic,structured-generation
Classifier: Intended Audience :: Developers
Classifier: License :: OSI Approved :: Apache Software License
Classifier: Programming Language :: Python :: 3
Classifier: Programming Language :: Python :: 3 :: Only
Classifier: Programming Language :: Python :: 3.11
Classifier: Programming Language :: Python :: 3.12
Classifier: Topic :: Software Development :: Libraries
Requires-Python: >=3.11
Requires-Dist: langchain-core<0.4,>=0.3.25
Requires-Dist: langgraph<0.4.0
Requires-Dist: pydantic>=2
Provides-Extra: openai
Requires-Dist: langchain-openai<0.4,>=0.3.33; extra == 'openai'
Requires-Dist: python-dotenv>=1; extra == 'openai'
Provides-Extra: test
Requires-Dist: pytest; extra == 'test'
